<core:FragmentDefinition xmlns="sap.m" xmlns:core="sap.ui.core">
	<ViewSettingsDialog confirm="onConfirmViewSettingsDialog">
		<sortItems >
			<!-- <ViewSettingsItem text="ID" key="id" selected="true"/> -->
			<ViewSettingsItem text="Project Name" key="attributes/name"/>
		</sortItems>
		<filterItems>
			<ViewSettingsFilterItem text="Status" key="attributes/status" multiSelect="false">
				<items>
					<ViewSettingsItem text="In-Progress" key="In-progress"/>
					<ViewSettingsItem text="Completed" key="Completed"/>
					<ViewSettingsItem text="New" key="New"/>
				</items>
			</ViewSettingsFilterItem>
	
			<!-- <ViewSettingsFilterItem text="Priority" key="attributes/priority" multiSelect="false">
				<items>
					<ViewSettingsItem text="High" key="High"/>
					<ViewSettingsItem text="Critical" key="Critical"/>
					<ViewSettingsItem text="Moderate" key="Moderate"/>
					<ViewSettingsItem text="Low" key="Low"/>
				</items>
			</ViewSettingsFilterItem> -->
		</filterItems>
	</ViewSettingsDialog>
</core:FragmentDefinition>